shrinktunes/__init__.py
shrinktunes/__main__.py
shrinktunes/cli.py
shrinktunes/ffmpeg.py
shrinktunes/tests/__init__.py
shrinktunes/tests/test_cli.py
shrinktunes/tests/test_ffmpeg.py
shrinktunes-0.1.0.dist-info/METADATA
shrinktunes-0.1.0.dist-info/WHEEL
shrinktunes-0.1.0.dist-info/entry_points.txt
shrinktunes-0.1.0.dist-info/RECORD
