Metadata-Version: 2.1
Name: shrinktunes
Version: 0.1.0
Summary: 
Author: Brian Jorgensen
Author-email: brian.jorgensen@gmail.com
Requires-Python: >=3.11,<4.0
Classifier: Programming Language :: Python :: 3
Classifier: Programming Language :: Python :: 3.11
Requires-Dist: rich (>=13.6.0,<14.0.0)
Requires-Dist: typer (>=0.9.0,<0.10.0)
